[
  {
    "name": "Programming Languages",
    "skills": [
      { "name": "Python", "level": 90 },
      { "name": "Java", "level": 85 },
      { "name": "C", "level": 80 },
      { "name": "C++", "level": 80 },
      { "name": "C#", "level": 75 },
      { "name": "R", "level": 70 },
      { "name": "TypeScript", "level": 85 },
      { "name": "JavaScript", "level": 90 },
      { "name": "SQL", "level": 85 }
    ]
  },
  {
    "name": "Web Development - Front-End",
    "skills": [
      { "name": "HTML5", "level": 90 },
      { "name": "CSS", "level": 85 },
      { "name": "React.js", "level": 85 },
      { "name": "Next.js", "level": 80 },
      { "name": "Responsive Web Design", "level": 90 }
    ]
  },
  {
    "name": "Web Development - Back-End",
    "skills": [
      { "name": "Node.js", "level": 80 },
      { "name": "Express.js", "level": 80 },
      { "name": "FastAPI", "level": 75 },
      { "name": "Django", "level": 75 }
    ]
  },
  {
    "name": "Full-Stack Development",
    "skills": [
      { "name": "End-to-End Development", "level": 85 }
    ]
  },
  {
    "name": "Database Management",
    "skills": [
      { "name": "PostgreSQL", "level": 85 },
      { "name": "MongoDB", "level": 80 },
      { "name": "RDBMS", "level": 80 },
      { "name": "Database Design", "level": 80 },
      { "name": "Database Development", "level": 80 },
      { "name": "JDBC", "level": 75 }
    ]
  },
  {
    "name": "API & Cloud Technologies",
    "skills": [
      { "name": "API Development", "level": 85 },
      { "name": "Plaid", "level": 70 },
      { "name": "Dwolla", "level": 70 },
      { "name": "Appwrite", "level": 75 },
      { "name": "Docker", "level": 75 },
      { "name": "AWS", "level": 80 }
    ]
  },
  {
    "name": "Software Development & Tools",
    "skills": [
      { "name": "Git", "level": 90 },
      { "name": "GitHub", "level": 90 },
      { "name": "GitHub Copilot", "level": 80 },
      { "name": "Version Control", "level": 90 },
      { "name": "Debugging", "level": 85 },
      { "name": "Implementation", "level": 80 },
      { "name": "Documentation", "level": 80 },
      { "name": "Mobile Development", "level": 85 }
    ]
  },
  {
    "name": "Security & DevOps",
    "skills": [
      { "name": "User Authentication", "level": 80 },
      { "name": "JWT", "level": 80 },
      { "name": "Security Best Practices", "level": 80 },
      { "name": "CI/CD Pipelines", "level": 70 }
    ]
  },
  {
    "name": "Other Technical Skills",
    "skills": [
      { "name": "OOP", "level": 85 },
      { "name": "Project Management", "level": 80 },
      { "name": "Operating Systems", "level": 75 },
      { "name": "WordPress", "level": 70 },
      { "name": "WordPress Design", "level": 70 }
    ]
  },
  {
    "name": "Soft Skills & Collaboration",
    "skills": [
      { "name": "Oral Communication", "level": 90 },
      { "name": "Teamwork", "level": 90 },
      { "name": "Problem-Solving", "level": 90 },
      { "name": "Project Management", "level": 85 }
    ]
  },
  {
    "name": "Languages",
    "skills": [
      { "name": "English", "level": 95 },
      { "name": "Urdu", "level": 90 },
      { "name": "Sindhi", "level": 85 },
      { "name": "Punjabi", "level": 85 }
    ]
  }
]